dephell-0.8.3.dist-info/dependency_links.txt
dephell-0.8.3.dist-info/entry_points.txt
dephell-0.8.3.dist-info/METADATA
dephell-0.8.3.dist-info/top_level.txt
dephell-0.8.3.dist-info/WHEEL
dephell/cli.py
dephell/context_tools.py
dephell/imports.py
dephell/cacher.py
dephell/__init__.py
dephell/exceptions.py
dephell/pip_cleaner.py
dephell/package_manager.py
dephell/__main__.py
dephell/constants.py
dephell/networking.py
dephell/cached_property.py
dephell/yaml.py
dephell/cache.py
dephell/logging_helpers.py
dephell/converters/pipfilelock.py
dephell/converters/pyproject.py
dephell/converters/pipfile.py
dephell/converters/conda.py
dephell/converters/poetry.py
dephell/converters/imports.py
dephell/converters/__init__.py
dephell/converters/setuppy.py
dephell/converters/wheel.py
dephell/converters/flit.py
dephell/converters/poetrylock.py
dephell/converters/base.py
dephell/converters/installed.py
dephell/converters/egginfo.py
dephell/converters/sdist.py
dephell/converters/pip.py
dephell/config/defaults.py
dephell/config/logging_config.py
dephell/config/manager.py
dephell/config/app_dirs.py
dephell/config/__init__.py
dephell/config/scheme.py
dephell/config/builders.py
dephell/repositories/_release.py
dephell/repositories/__init__.py
dephell/repositories/_getter.py
dephell/repositories/base.py
dephell/repositories/_local.py
dephell/repositories/_conda/_git.py
dephell/repositories/_conda/_cloud.py
dephell/repositories/_conda/_base.py
dephell/repositories/_conda/_composite.py
dephell/repositories/_conda/__init__.py
dephell/repositories/_git/bitbucket.py
dephell/repositories/_git/gitlab.py
dephell/repositories/_git/github.py
dephell/repositories/_git/__init__.py
dephell/repositories/_git/git.py
dephell/repositories/_warehouse/_simple.py
dephell/repositories/_warehouse/_base.py
dephell/repositories/_warehouse/__init__.py
dephell/repositories/_warehouse/_api.py
dephell/repositories/_warehouse/_local.py
dephell/controllers/_resolver.py
dephell/controllers/_readme.py
dephell/controllers/_dependency.py
dephell/controllers/_safety.py
dephell/controllers/_mutator.py
dephell/controllers/_uploader.py
dephell/controllers/__init__.py
dephell/controllers/_graph.py
dephell-0.8.3.dist-info/LICENSE
dephell-0.8.3.dist-info/RECORD