Metadata-Version: 2.1
Name: dephell
Version: 0.8.3
Summary: Dependency resolution for Python
Project-URL: Homepage, https://dephell.org/
Project-URL: Repository, https://github.com/dephell/dephell
Project-URL: Documentation, https://dephell.org/docs/
Author: Gram
Author-email: master_fess@mail.ru
License: MIT
Requires-Python: >=3.6
Keywords: dephell,packaging,dependency,dependencies,venv,licenses,pip,poetry,pipfile,pipenv,setuptools
Classifier: Development Status :: 4 - Beta
Classifier: Environment :: Console
Classifier: Framework :: Setuptools Plugin
Classifier: Intended Audience :: Developers
Classifier: License :: OSI Approved :: MIT License
Classifier: Programming Language :: Python
Classifier: Programming Language :: Python :: 3.6
Classifier: Programming Language :: Python :: 3.7
Classifier: Programming Language :: Python :: 3.8
Classifier: Topic :: Security
Classifier: Topic :: Software Development :: Build Tools
Classifier: Topic :: Software Development :: Libraries :: Python Modules
Requires-Dist: aiofiles; extra == "full"
Requires-Dist: aiohttp
Requires-Dist: aioresponses; extra == "tests" or extra == "dev"
Requires-Dist: alabaster; extra == "docs" or extra == "dev"
Requires-Dist: appdirs; extra == "full"
Requires-Dist: attrs>=19.2.0
Requires-Dist: autopep8; extra == "full"
Requires-Dist: bowler; extra == "full"
Requires-Dist: cerberus>=1.3
Requires-Dist: certifi
Requires-Dist: colorama; extra == "full"
Requires-Dist: dephell-archive>=0.1.5
Requires-Dist: dephell-argparse>=0.1.1
Requires-Dist: dephell-changelogs
Requires-Dist: dephell-discover>=0.2.6
Requires-Dist: dephell-licenses>=0.1.6
Requires-Dist: dephell-links>=0.1.4
Requires-Dist: dephell-markers>=1.0.0
Requires-Dist: dephell-pythons>=0.1.11
Requires-Dist: dephell-setuptools>=0.2.1
Requires-Dist: dephell-shells>=0.1.3
Requires-Dist: dephell-specifier>=0.1.7
Requires-Dist: dephell-venvs>=0.1.16
Requires-Dist: dephell-versioning
Requires-Dist: docker; extra == "full"
Requires-Dist: dockerpty; extra == "full"
Requires-Dist: fissix; extra == "full"
Requires-Dist: flake8-isort; extra == "dev"
Requires-Dist: graphviz; extra == "full"
Requires-Dist: html5lib; extra == "full"
Requires-Dist: isort[pyproject]; extra == "dev"
Requires-Dist: jinja2
Requires-Dist: m2r
Requires-Dist: packaging
Requires-Dist: pip<=19.3.1,>=18.0
Requires-Dist: pygments; extra == "full"
Requires-Dist: pygments-github-lexers; extra == "docs" or extra == "dev"
Requires-Dist: pytest; extra == "tests" or extra == "dev"
Requires-Dist: python-gnupg; extra == "full"
Requires-Dist: recommonmark; extra == "docs" or extra == "dev"
Requires-Dist: requests
Requires-Dist: requests-mock; extra == "tests" or extra == "dev"
Requires-Dist: ruamel.yaml
Requires-Dist: sphinx; extra == "docs" or extra == "dev"
Requires-Dist: tabulate; extra == "full"
Requires-Dist: tomlkit
Requires-Dist: yapf; extra == "full"
Requires-Dist: yaspin
Provides-Extra: dev
Provides-Extra: docs
Provides-Extra: full
Provides-Extra: tests
